expon/__init__.py
expon/asset/default.css
expon/asset/github.css
expon/core/__init__.py
expon/core/exp.py
expon/core/metric.py
expon/core/params.py
expon/log/__init__.py
expon/log/logging.py
expon/utils/__init__.py
expon/utils/file.py
expon/utils/gconfig.py
expon/utils/git.py
expon/utils/md.py
expon/utils/random.py
expon/utils/time.py
expon/utils/vis.py
expon-0.0.7.dist-info/LICENSE
expon-0.0.7.dist-info/METADATA
expon-0.0.7.dist-info/WHEEL
expon-0.0.7.dist-info/top_level.txt
expon-0.0.7.dist-info/RECORD
