Metadata-Version: 2.1
Name: expon
Version: 0.0.7
Summary: Experiment tool for deep learning (PyTorch).
Home-page: https://github.com/hi-zhenyu/expon
Author: Zhenyu Huang
Author-email: zyhuang.gm@gmail.com
License: UNKNOWN
Platform: UNKNOWN
Classifier: Programming Language :: Python :: 3
Classifier: License :: OSI Approved :: MIT License
Classifier: Operating System :: OS Independent
Requires-Python: >=3.6
Requires-Dist: markdown
Requires-Dist: numpy
Requires-Dist: matplotlib
